mlkit_lyt/__init__.py
mlkit_lyt/KNN/__init__.py
mlkit_lyt/KNN/_kd_tree.py
mlkit_lyt/KNN/_knn.py
mlkit_lyt/common/__init__.py
mlkit_lyt/common/_process.py
mlkit_lyt/common/_stat.py
mlkit_lyt/logistic/__init__.py
mlkit_lyt/logistic/_logistic.py
mlkit_lyt-0.0.3.dist-info/LICENSE
mlkit_lyt-0.0.3.dist-info/METADATA
mlkit_lyt-0.0.3.dist-info/WHEEL
mlkit_lyt-0.0.3.dist-info/top_level.txt
mlkit_lyt-0.0.3.dist-info/RECORD
