Metadata-Version: 2.1
Name: mlkit_lyt
Version: 0.0.3
Summary: Machine Learning in Python
Home-page: http://lyt0628.icu
Download-URL: http://github.com//LYT0628/mllearn
Author: lyt0628
Author-email: lyt0628 <lyt.0628@qq.com>
License: BSD 2-Clause License
Project-URL: Repository, https://github.com/LYT0628/mllearn
Project-URL: Documentation, http://lyt0628.icu/docs/mllearn
Project-URL: Issues, https://github.com/LYT0628/mllearn/issues
Project-URL: Official Website, https://lyt0628.icu
Keywords: ml,machine learning
Classifier: Development Status :: 1 - Planning
Classifier: Programming Language :: Python :: 3
Classifier: License :: OSI Approved :: BSD License
Classifier: Operating System :: OS Independent
Classifier: Natural Language :: Chinese (Simplified)
Classifier: Topic :: Utilities
Requires-Python: >=3.8
License-File: LICENSE
Requires-Dist: numpy
